emailage/__init__.py
emailage/client.py
emailage/signature.py
emailage/validation.py
emailage/test/__init__.py
emailage/test/client_test.py
emailage/test/conftest.py
emailage/test/integration_test.py
emailage/test/signature_test.py
emailage/test/validation_test.py
emailage_official-1.1.5.dist-info/METADATA
emailage_official-1.1.5.dist-info/RECORD
emailage_official-1.1.5.dist-info/WHEEL
emailage_official-1.1.5.dist-info/entry_points.txt
emailage_official-1.1.5.dist-info/top_level.txt
