Metadata-Version: 2.1
Name: emailage-official
Version: 1.1.5
Summary: Official Emailage API client written in Python
Home-page: https://www.emailage.com/
Author: Emailage Dev Team
Author-email: dev@emailage.com
License: MIT
Platform: UNKNOWN
Classifier: Development Status :: 5 - Production/Stable
Classifier: License :: OSI Approved :: MIT License
Classifier: Natural Language :: English
Classifier: Operating System :: OS Independent
Classifier: Programming Language :: Python
Classifier: Programming Language :: Python :: 2
Classifier: Programming Language :: Python :: 2.7
Classifier: Programming Language :: Python :: 3
Classifier: Programming Language :: Python :: 3.3
Classifier: Programming Language :: Python :: 3.4
Classifier: Programming Language :: Python :: 3.5
Classifier: Programming Language :: Python :: 3.6
Classifier: Programming Language :: Python :: 3.7
Requires-Dist: requests (>=2.9)
Requires-Dist: mock (>=2.0)
Requires-Dist: six (==1.10.0)
